Metadata-Version: 2.4
Name: bergson
Version: 0.5.1
Summary: Tracing the memory of neural nets with data attribution
License: MIT License
Keywords: interpretability,explainable-ai
Requires-Python: >=3.10
License-File: LICENSE
Requires-Dist: accelerate
Requires-Dist: datasets
Requires-Dist: jaxtyping>=0.3.3
Requires-Dist: ml_dtypes
Requires-Dist: natsort
Requires-Dist: numpy
Requires-Dist: peft>=0.17.0
Requires-Dist: pyarrow
Requires-Dist: simple-parsing
Requires-Dist: torch
Requires-Dist: transformers<4.56.0
Provides-Extra: dev
Requires-Dist: pre-commit; extra == "dev"
Requires-Dist: pytest; extra == "dev"
Requires-Dist: pyright; extra == "dev"
Requires-Dist: trl; extra == "dev"
Requires-Dist: furo; extra == "dev"
Requires-Dist: myst-parser; extra == "dev"
Requires-Dist: sphinx; extra == "dev"
Requires-Dist: sphinx-autodoc-typehints; extra == "dev"
Requires-Dist: sphinx-rtd-theme; extra == "dev"
Requires-Dist: nbsphinx; extra == "dev"
Requires-Dist: torch-tb-profiler>=0.4.3; extra == "dev"
Provides-Extra: benchmarks
Requires-Dist: wandb; extra == "benchmarks"
Requires-Dist: kronfluence; extra == "benchmarks"
Requires-Dist: dattri; extra == "benchmarks"
Provides-Extra: example
Requires-Dist: backoff>=2.2.1; extra == "example"
Requires-Dist: bitsandbytes>=0.49.0; extra == "example"
Requires-Dist: pydantic>=2.12.5; extra == "example"
Requires-Dist: trl; extra == "example"
Provides-Extra: faiss
Requires-Dist: faiss-gpu-cu12; extra == "faiss"
Dynamic: license-file
